pychometrics/__init__.py
pychometrics/analysis.py
pychometrics/report.py
pychometrics/tests/__init__.py
pychometrics/tests/test_assessment_analysis.py
pychometrics-0.2.1.dist-info/LICENSE.txt
pychometrics-0.2.1.dist-info/METADATA
pychometrics-0.2.1.dist-info/WHEEL
pychometrics-0.2.1.dist-info/top_level.txt
pychometrics-0.2.1.dist-info/RECORD
